Metadata-Version: 2.1
Name: plug-email-chase
Version: 1.0.1
Summary: Plug - Email Chase Pipeline
Home-page: https://github.com/lollococce/plug-email-chase
Author: Lorenzo Coacci
Author-email: lorenzo@coacci.it
License: 
Keywords: data pipeline,etl,data engineering
Platform: UNKNOWN
Classifier: Programming Language :: Python :: 3 :: Only
Classifier: License :: OSI Approved :: MIT License
Classifier: Natural Language :: English
Provides-Extra: dev
